{"Year":[2012,2013,2014,2015,2016,2017,2018,2019,2020,2021,2012,2013,2014,2015,2016,2017,2018,2019,2020,2021,2012,2013,2014,2015,2016,2017,2018,2019,2020,2021,2012,2013,2014,2015,2016,2017,2018,2019,2020,2021,2012,2013,2014,2015,2016,2017,2018,2019,2020,2021,2012,2013,2014,2015,2016,2017,2018,2019,2020,2021,2012,2013,2014,2015,2016,2017,2018,2019,2020,2021],"SERIES":["List of endangered species","List of endangered species","List of endangered species","List of endangered species","List of endangered species","List of endangered species","List of endangered species","List of endangered species","List of endangered species","List of endangered species","List of endangered species","List of endangered species","List of endangered species","List of endangered species","List of endangered species","List of endangered species","List of endangered species","List of endangered species","List of endangered species","List of endangered species","List of endangered species","List of endangered species","List of endangered species","List of endangered species","List of endangered species","List of endangered species","List of endangered species","List of endangered species","List of endangered species","List of endangered species","List of endangered species","List of endangered species","List of endangered species","List of endangered species","List of endangered species","List of endangered species","List of endangered species","List of endangered species","List of endangered species","List of endangered species","List of endangered species","List of endangered species","List of endangered species","List of endangered species","List of endangered species","List of endangered species","List of endangered species","List of endangered species","List of endangered species","List of endangered species","List of endangered species","List of endangered species","List of endangered species","List of endangered species","List of endangered species","List of endangered species","List of endangered species","List of endangered species","List of endangered species","List of endangered species","List of endangered species","List of endangered species","List of endangered species","List of endangered species","List of endangered species","List of endangered species","List of endangered species","List of endangered species","List of endangered species","List of endangered species"],"UNIT_MEASURE":["Number","Number","Number","Number","Number","Number","Number","Number","Number","Number","Number","Number","Number","Number","Number","Number","Number","Number","Number","Number","Number","Number","Number","Number","Number","Number","Number","Number","Number","Number","Number","Number","Number","Number","Number","Number","Number","Number","Number","Number","Number","Number","Number","Number","Number","Number","Number","Number","Number","Number","Number","Number","Number","Number","Number","Number","Number","Number","Number","Number","Number","Number","Number","Number","Number","Number","Number","Number","Number","Number"],"COMPOSITE_BREAKDOWN":["Invertebrates (Inverttebratae)","Invertebrates (Inverttebratae)","Invertebrates (Inverttebratae)","Invertebrates (Inverttebratae)","Invertebrates (Inverttebratae)","Invertebrates (Inverttebratae)","Invertebrates (Inverttebratae)","Invertebrates (Inverttebratae)","Invertebrates (Inverttebratae)","Invertebrates (Inverttebratae)","Reptiles (Reptiles)","Reptiles (Reptiles)","Reptiles (Reptiles)","Reptiles (Reptiles)","Reptiles (Reptiles)","Reptiles (Reptiles)","Reptiles (Reptiles)","Reptiles (Reptiles)","Reptiles (Reptiles)","Reptiles (Reptiles)","Amphibians (Amphibia)","Amphibians (Amphibia)","Amphibians (Amphibia)","Amphibians (Amphibia)","Amphibians (Amphibia)","Amphibians (Amphibia)","Amphibians (Amphibia)","Amphibians (Amphibia)","Amphibians (Amphibia)","Amphibians (Amphibia)","Mammals (Mammals)","Mammals (Mammals)","Mammals (Mammals)","Mammals (Mammals)","Mammals (Mammals)","Mammals (Mammals)","Mammals (Mammals)","Mammals (Mammals)","Mammals (Mammals)","Mammals (Mammals)","Fish (Pisces)","Fish (Pisces)","Fish (Pisces)","Fish (Pisces)","Fish (Pisces)","Fish (Pisces)","Fish (Pisces)","Fish (Pisces)","Fish (Pisces)","Fish (Pisces)","Birds (Aves)","Birds (Aves)","Birds (Aves)","Birds (Aves)","Birds (Aves)","Birds (Aves)","Birds (Aves)","Birds (Aves)","Birds (Aves)","Birds (Aves)","Vascular plants (Planate)","Vascular plants (Planate)","Vascular plants (Planate)","Vascular plants (Planate)","Vascular plants (Planate)","Vascular plants (Planate)","Vascular plants (Planate)","Vascular plants (Planate)","Vascular plants (Planate)","Vascular plants (Planate)"],"Value":[308,308,308,308,308,308,308,308,308,308,25,25,25,25,25,25,25,25,25,25,20,20,20,20,20,20,20,20,20,20,57,57,57,57,57,57,57,57,57,57,48,48,48,48,48,48,48,48,48,48,304,304,304,304,304,304,304,304,304,304,818,818,818,818,818,818,818,818,818,818]}